arcade_hubspot/__init__.py
arcade_hubspot/constants.py
arcade_hubspot/custom_critics.py
arcade_hubspot/enums.py
arcade_hubspot/exceptions.py
arcade_hubspot/properties.py
arcade_hubspot/http_client/__init__.py
arcade_hubspot/http_client/client_helpers.py
arcade_hubspot/http_client/http_client.py
arcade_hubspot/http_client/list_helpers.py
arcade_hubspot/models/__init__.py
arcade_hubspot/models/crm_api_models.py
arcade_hubspot/models/system_api_models.py
arcade_hubspot/models/tool_models.py
arcade_hubspot/tool_utils/__init__.py
arcade_hubspot/tool_utils/activities_helper.py
arcade_hubspot/tool_utils/company_utils.py
arcade_hubspot/tool_utils/contact_utils.py
arcade_hubspot/tool_utils/deal_utils.py
arcade_hubspot/tool_utils/pipeline_utils.py
arcade_hubspot/tool_utils/search_activities_helper.py
arcade_hubspot/tool_utils/shared_utils.py
arcade_hubspot/tools/__init__.py
arcade_hubspot/tools/system_context.py
arcade_hubspot/tools/users.py
arcade_hubspot/tools/crm/activities.py
arcade_hubspot/tools/crm/companies.py
arcade_hubspot/tools/crm/contacts.py
arcade_hubspot/tools/crm/deals.py
arcade_hubspot/tools/crm/pipelines.py
arcade_hubspot/tools/crm/search_activities.py
arcade_hubspot/utils/__init__.py
arcade_hubspot/utils/data_utils.py
arcade_hubspot/utils/gui_url_builder.py
arcade_hubspot-3.0.0.dist-info/METADATA
arcade_hubspot-3.0.0.dist-info/WHEEL
arcade_hubspot-3.0.0.dist-info/licenses/LICENSE
arcade_hubspot-3.0.0.dist-info/RECORD
